pyedid/__init__.py
pyedid/helpers/__init__.py
pyedid/types/__init__.py
pyedid/types/default.py
pyedid/types/edid.py
pyedid/types/registry.py
pyedid-1.0.3.dist-info/LICENSE
pyedid-1.0.3.dist-info/METADATA
pyedid-1.0.3.dist-info/WHEEL
pyedid-1.0.3.dist-info/top_level.txt
pyedid-1.0.3.dist-info/RECORD
