Metadata-Version: 2.1
Name: pyedid
Version: 1.0.3
Summary: Library to parse extended display identification data (EDID)
Home-page: https://github.com/dd4e/pyedid
Author: Davydov Denis, Jonas Lieb
Author-email: dadmoscow@gmail.com
License: MIT
Keywords: edid,xrandr,display,monitor
Classifier: Development Status :: 5 - Production/Stable
Classifier: License :: OSI Approved :: MIT License
Classifier: Operating System :: POSIX :: Linux
Classifier: Programming Language :: Python :: 3.6
Classifier: Programming Language :: Python :: 3.7
Classifier: Programming Language :: Python :: 3.8
Classifier: Programming Language :: Python :: 3.9
Classifier: Topic :: Software Development :: Libraries
Classifier: Topic :: System :: Hardware
License-File: LICENSE
